dhnn.py
dhnn-0.1.12.dist-info/LICENSE
dhnn-0.1.12.dist-info/METADATA
dhnn-0.1.12.dist-info/WHEEL
dhnn-0.1.12.dist-info/top_level.txt
dhnn-0.1.12.dist-info/RECORD
