Metadata-Version: 2.1
Name: dhnn
Version: 0.1.12
Summary: A Discrete Hopfield Neural Network Framework in python.
Home-page: https://github.com/Zeroto521/DHNN
Author: yosukekatada,Zeroto521
Author-email: Zeroto521@gmail.com
Maintainer: Zero
Maintainer-email: Zeroto521@gmail.com
License: MIT
Download-URL: https://github.com/Zeroto521/DHNN/archive/master.zip
Platform: Windows
Platform: MacOS
Platform: Unix
Classifier: Development Status :: 4 - Beta
Classifier: Intended Audience :: Developers
Classifier: Intended Audience :: Education
Classifier: Intended Audience :: Science/Research
Classifier: License :: OSI Approved :: MIT License
Classifier: Natural Language :: English
Classifier: Natural Language :: Chinese (Simplified)
Classifier: Operating System :: Microsoft :: Windows
Classifier: Operating System :: MacOS
Classifier: Operating System :: Unix
Classifier: Programming Language :: Python
Classifier: Programming Language :: Python :: 2
Classifier: Programming Language :: Python :: 2.7
Classifier: Programming Language :: Python :: 3
Classifier: Programming Language :: Python :: 3.4
Classifier: Programming Language :: Python :: 3.5
Classifier: Programming Language :: Python :: 3.6
Classifier: Topic :: Software Development :: Libraries
Classifier: Topic :: Software Development :: Libraries :: Python Modules
Requires: numpy
